thRSAhold/__init__.py
thRSAhold/thRSAhold.py
thRSAhold-0.1.0.dist-info/LICENSE
thRSAhold-0.1.0.dist-info/METADATA
thRSAhold-0.1.0.dist-info/WHEEL
thRSAhold-0.1.0.dist-info/top_level.txt
thRSAhold-0.1.0.dist-info/RECORD
