Metadata-Version: 2.1
Name: thRSAhold
Version: 0.1.0
Summary: A Hybrid RSA Threshold Encryption Library
Author-email: Eric Wagner <eric.wagner@fkie.fraunhofer.de>
License: GPLv3
Project-URL: Homepage, https://github.com/eric-wagner/thRSAhold
Keywords: threshold,encryption,RSA,AES
Requires-Python: >=3.7
License-File: LICENSE
Requires-Dist: pycryptodome
